{
    "key": "group_5d34a8b296084",
    "title": "Alert Details",
    "fields": [
        {
            "key": "field_5d34a8d97cacc",
            "label": "Alert Type",
            "name": "alert_type",
            "type": "select",
            "instructions": "",
            "required": 0,
            "conditional_logic": 0,
            "wrapper": {
                "width": "",
                "class": "",
                "id": ""
            },
            "choices": {
                "none": "Informational (no Icon)",
                "medium": "Medium",
                "high": "High"
            },
            "default_value": false,
            "allow_null": 0,
            "multiple": 0,
            "ui": 0,
            "return_format": "value",
            "ajax": 0,
            "placeholder": ""
        },
        {
            "key": "field_5d9f4a4841a08",
            "label": "Display on Home Page Only",
            "name": "home_page_only",
            "type": "true_false",
            "instructions": "Check to display Alert on the home page:",
            "required": 0,
            "conditional_logic": 0,
            "wrapper": {
                "width": "",
                "class": "",
                "id": ""
            },
            "message": "",
            "default_value": 0,
            "ui": 0,
            "ui_on_text": "",
            "ui_off_text": ""
        },
        {
            "key": "field_5d34a9137cacd",
            "label": "Alert Start Date",
            "name": "alert_start_date",
            "type": "date_picker",
            "instructions": "",
            "required": 0,
            "conditional_logic": 0,
            "wrapper": {
                "width": "50",
                "class": "",
                "id": ""
            },
            "display_format": "m\/d\/Y",
            "return_format": "F j, Y",
            "first_day": 0
        },
        {
            "key": "field_5d34a9407cace",
            "label": "Alert End Date",
            "name": "alert_end_date",
            "type": "date_picker",
            "instructions": "",
            "required": 0,
            "conditional_logic": 0,
            "wrapper": {
                "width": "50",
                "class": "",
                "id": ""
            },
            "display_format": "m\/d\/Y",
            "return_format": "F j, Y",
            "first_day": 0
        },
        {
            "key": "field_5d34ada846532",
            "label": "Community Locations",
            "name": "community_locations",
            "type": "relationship",
            "instructions": "",
            "required": 0,
            "conditional_logic": 0,
            "wrapper": {
                "width": "",
                "class": "",
                "id": ""
            },
            "post_type": [
                "community"
            ],
            "taxonomy": "",
            "filters": "",
            "elements": "",
            "min": "",
            "max": "",
            "return_format": "object"
        }
    ],
    "location": [
        [
            {
                "param": "post_type",
                "operator": "==",
                "value": "alert"
            }
        ]
    ],
    "menu_order": 0,
    "position": "normal",
    "style": "default",
    "label_placement": "top",
    "instruction_placement": "label",
    "hide_on_screen": "",
    "active": true,
    "description": "",
    "modified": 1604003655
}